pushsource/__init__.py
pushsource/_impl/__init__.py
pushsource/_impl/compat_attr.py
pushsource/_impl/helpers.py
pushsource/_impl/list_cmd.py
pushsource/_impl/reader.py
pushsource/_impl/source.py
pushsource/_impl/validator.py
pushsource/_impl/backend/__init__.py
pushsource/_impl/backend/broken_rpmlib.py
pushsource/_impl/backend/direct.py
pushsource/_impl/backend/koji_containers.py
pushsource/_impl/backend/koji_source.py
pushsource/_impl/backend/modulemd.py
pushsource/_impl/backend/registry_source.py
pushsource/_impl/backend/errata_source/__init__.py
pushsource/_impl/backend/errata_source/errata_client.py
pushsource/_impl/backend/errata_source/errata_source.py
pushsource/_impl/backend/pub_source/__init__.py
pushsource/_impl/backend/pub_source/pub_client.py
pushsource/_impl/backend/pub_source/pub_source.py
pushsource/_impl/backend/staged/__init__.py
pushsource/_impl/backend/staged/staged_ami.py
pushsource/_impl/backend/staged/staged_base.py
pushsource/_impl/backend/staged/staged_cgw.py
pushsource/_impl/backend/staged/staged_cloud.py
pushsource/_impl/backend/staged/staged_compsxml.py
pushsource/_impl/backend/staged/staged_errata.py
pushsource/_impl/backend/staged/staged_files.py
pushsource/_impl/backend/staged/staged_modulemd.py
pushsource/_impl/backend/staged/staged_productid.py
pushsource/_impl/backend/staged/staged_rpm.py
pushsource/_impl/backend/staged/staged_source.py
pushsource/_impl/backend/staged/staged_unsupported.py
pushsource/_impl/backend/staged/staged_utils.py
pushsource/_impl/model/__init__.py
pushsource/_impl/model/ami.py
pushsource/_impl/model/azure.py
pushsource/_impl/model/base.py
pushsource/_impl/model/cache.py
pushsource/_impl/model/cgw.py
pushsource/_impl/model/comps.py
pushsource/_impl/model/container.py
pushsource/_impl/model/conv.py
pushsource/_impl/model/directory.py
pushsource/_impl/model/erratum.py
pushsource/_impl/model/erratum_fixup.py
pushsource/_impl/model/file.py
pushsource/_impl/model/modulemd.py
pushsource/_impl/model/productid.py
pushsource-2.52.1.dist-info/licenses/LICENSE
pushsource-2.52.1.dist-info/METADATA
pushsource-2.52.1.dist-info/WHEEL
pushsource-2.52.1.dist-info/entry_points.txt
pushsource-2.52.1.dist-info/top_level.txt
pushsource-2.52.1.dist-info/RECORD
