Metadata-Version: 2.4
Name: pushsource
Version: 2.52.1
Summary: A library to load push items from a variety of sources
Home-page: https://github.com/release-engineering/pushsource
License: GNU General Public License
Project-URL: Documentation, https://release-engineering.github.io/pushsource/
Project-URL: Changelog, https://github.com/release-engineering/pushsource/blob/master/CHANGELOG.md
Classifier: Development Status :: 5 - Production/Stable
Classifier: Intended Audience :: Developers
Classifier: License :: OSI Approved :: GNU General Public License v3 or later (GPLv3+)
Classifier: Programming Language :: Python :: 3
Classifier: Topic :: Software Development :: Libraries :: Python Modules
Requires-Python: >=3.6
License-File: LICENSE
Requires-Dist: attrs
Requires-Dist: cryptography
Requires-Dist: frozendict; python_version >= "3.6"
Requires-Dist: frozenlist2
Requires-Dist: kobo
Requires-Dist: koji>=1.18
Requires-Dist: more-executors>=2.7.0
Requires-Dist: pushcollector
Requires-Dist: pyasn1
Requires-Dist: python-dateutil
Requires-Dist: pytz; python_version < "3.9"
Requires-Dist: PyYAML
Requires-Dist: requests
Dynamic: classifier
Dynamic: description
Dynamic: description-content-type
Dynamic: home-page
Dynamic: license
Dynamic: license-file
Dynamic: project-url
Dynamic: requires-dist
Dynamic: requires-python
Dynamic: summary
